dpgextended.py
dpgkeywords.py
jsontodpg.py
tokenizer.py
jsontodpg-1.9.dist-info/METADATA
jsontodpg-1.9.dist-info/WHEEL
jsontodpg-1.9.dist-info/top_level.txt
jsontodpg-1.9.dist-info/RECORD
